odoo/addons/l10n_br_account_payment_order/README.rst
odoo/addons/l10n_br_account_payment_order/__init__.py
odoo/addons/l10n_br_account_payment_order/__manifest__.py
odoo/addons/l10n_br_account_payment_order/constants.py
odoo/addons/l10n_br_account_payment_order/data/boleto_data.xml
odoo/addons/l10n_br_account_payment_order/data/cnab_data.xml
odoo/addons/l10n_br_account_payment_order/data/l10n_br_payment_export_type.xml
odoo/addons/l10n_br_account_payment_order/data/cnab_codes/banco_ailos_cnab_240.xml
odoo/addons/l10n_br_account_payment_order/data/cnab_codes/banco_bradesco_cnab_240_400.xml
odoo/addons/l10n_br_account_payment_order/data/cnab_codes/banco_cef_cnab_240.xml
odoo/addons/l10n_br_account_payment_order/data/cnab_codes/banco_do_brasil_cnab_400.xml
odoo/addons/l10n_br_account_payment_order/data/cnab_codes/banco_itau_cnab_240_400.xml
odoo/addons/l10n_br_account_payment_order/data/cnab_codes/banco_sicred_cnab_240.xml
odoo/addons/l10n_br_account_payment_order/data/cnab_codes/banco_unicred_cnab_240_400.xml
odoo/addons/l10n_br_account_payment_order/demo/account_account.xml
odoo/addons/l10n_br_account_payment_order/demo/account_invoice.xml
odoo/addons/l10n_br_account_payment_order/demo/account_journal.xml
odoo/addons/l10n_br_account_payment_order/demo/account_payment_method.xml
odoo/addons/l10n_br_account_payment_order/demo/account_payment_mode.xml
odoo/addons/l10n_br_account_payment_order/demo/account_payment_order.xml
odoo/addons/l10n_br_account_payment_order/demo/ir_sequence.xml
odoo/addons/l10n_br_account_payment_order/demo/mov_instruction_code.xml
odoo/addons/l10n_br_account_payment_order/demo/res_partner_bank.xml
odoo/addons/l10n_br_account_payment_order/demo/res_users.xml
odoo/addons/l10n_br_account_payment_order/i18n/l10n_br_account_payment_order.pot
odoo/addons/l10n_br_account_payment_order/migrations/12.0.2.0.0/pre-migration.py
odoo/addons/l10n_br_account_payment_order/migrations/12.0.3.0.0/pre-migration.py
odoo12_addon_l10n_br_account_payment_order-12.0.9.1.1.dist-info/METADATA
odoo12_addon_l10n_br_account_payment_order-12.0.9.1.1.dist-info/WHEEL
odoo12_addon_l10n_br_account_payment_order-12.0.9.1.1.dist-info/top_level.txt
odoo12_addon_l10n_br_account_payment_order-12.0.9.1.1.dist-info/RECORD
