Metadata-Version: 2.1
Name: odoo12-addon-l10n_br_account_payment_order
Version: 12.0.9.1.1
Summary: Brazilian Payment Order
Home-page: https://github.com/OCA/l10n-brazil
Author: KMEE, Akretion, Odoo Community Association (OCA)
Author-email: support@odoo-community.org
License: AGPL-3
Classifier: Programming Language :: Python
Classifier: Framework :: Odoo
Classifier: Framework :: Odoo :: 12.0
Classifier: License :: OSI Approved :: GNU Affero General Public License v3
Requires-Python: >=3.5
Requires-Dist: odoo12-addon-account-payment-order
Requires-Dist: odoo12-addon-l10n-br-account-due-list
Requires-Dist: odoo12-addon-l10n-br-base
Requires-Dist: odoo <12.1dev,>=12.0a
